sirup/IPRotator.py
sirup/TemporaryFileWithRootPermission.py
sirup/VPNConnector.py
sirup/__init__.py
sirup/raise_ovpn_exceptions.py
sirup/utils.py
sirup-0.2.4.dist-info/LICENSE
sirup-0.2.4.dist-info/METADATA
sirup-0.2.4.dist-info/WHEEL
sirup-0.2.4.dist-info/top_level.txt
sirup-0.2.4.dist-info/RECORD
